auto_optional/__init__.py
auto_optional/code_processing.py
auto_optional/cst_helper.py
auto_optional/data_structures.py
auto_optional/file_handling.py
auto_optional/main.py
auto_optional/py.typed
auto_optional-0.3.2.dist-info/entry_points.txt
auto_optional-0.3.2.dist-info/LICENSE
auto_optional-0.3.2.dist-info/WHEEL
auto_optional-0.3.2.dist-info/METADATA
auto_optional-0.3.2.dist-info/RECORD
