Metadata-Version: 2.1
Name: auto-optional
Version: 0.3.2
Summary: Adds the Optional type-hint to arguments where the default value is None
Home-page: https://auto-optional.daanluttik.nl
Author: Luttik
Author-email: dtluttik@gmail.com
Requires-Python: >3.7,<4.0
Classifier: Programming Language :: Python :: 3
Classifier: Programming Language :: Python :: 3.10
Classifier: Programming Language :: Python :: 3.8
Classifier: Programming Language :: Python :: 3.9
Requires-Dist: libcst (>=0.3.20,<0.4.0)
Requires-Dist: typer (>=0.4.0,<0.5.0)
Project-URL: Documentation, https://auto-optional.daanluttik.nl
Project-URL: Repository, https://github.com/Luttik/auto-optional
